sundar_gap_stat/__init__.py
sundar_gap_stat/sundar_gap_stat.py
sundar_gap_stat-2.0.0.dist-info/licenses/LICENSE
sundar_gap_stat-2.0.0.dist-info/METADATA
sundar_gap_stat-2.0.0.dist-info/WHEEL
sundar_gap_stat-2.0.0.dist-info/top_level.txt
sundar_gap_stat-2.0.0.dist-info/RECORD
