Metadata-Version: 2.4
Name: sundar-gap-stat
Version: 2.0.0
Summary: Sundar-Tibshirani Gap Statistic for evaluating any cluster solution
Author-email: "P.V. Sundar Balakrishnan" <sundar@uw.edu>
Maintainer-email: "P.V. Sundar Balakrishnan" <sundar@uw.edu>
License: MIT
Project-URL: Homepage, https://github.com/pvsundar/sundar_gap_stat
Project-URL: Documentation, https://github.com/pvsundar/sundar_gap_stat#readme
Project-URL: Repository, https://github.com/pvsundar/sundar_gap_stat
Project-URL: Issues, https://github.com/pvsundar/sundar_gap_stat/issues
Keywords: clustering,cluster-analysis,gap-statistic,machine-learning,data-science,market-segmentation,customer-analytics,unsupervised-learning
Classifier: Development Status :: 5 - Production/Stable
Classifier: Intended Audience :: Science/Research
Classifier: Intended Audience :: Developers
Classifier: License :: OSI Approved :: MIT License
Classifier: Operating System :: OS Independent
Classifier: Programming Language :: Python :: 3
Classifier: Programming Language :: Python :: 3.8
Classifier: Programming Language :: Python :: 3.9
Classifier: Programming Language :: Python :: 3.10
Classifier: Programming Language :: Python :: 3.11
Classifier: Programming Language :: Python :: 3.12
Classifier: Topic :: Scientific/Engineering
Classifier: Topic :: Scientific/Engineering :: Artificial Intelligence
Classifier: Topic :: Scientific/Engineering :: Information Analysis
Requires-Python: >=3.8
License-File: LICENSE
Requires-Dist: numpy>=1.20.0
Requires-Dist: scipy>=1.7.0
Requires-Dist: scikit-learn>=1.0.0
Provides-Extra: test
Requires-Dist: pytest>=7.0.0; extra == "test"
Requires-Dist: pytest-cov>=4.0.0; extra == "test"
Provides-Extra: dev
Requires-Dist: pytest>=7.0.0; extra == "dev"
Requires-Dist: pytest-cov>=4.0.0; extra == "dev"
Requires-Dist: black>=23.0.0; extra == "dev"
Requires-Dist: flake8>=6.0.0; extra == "dev"
Requires-Dist: mypy>=1.0.0; extra == "dev"
Provides-Extra: examples
Requires-Dist: matplotlib>=3.5.0; extra == "examples"
Requires-Dist: seaborn>=0.12.0; extra == "examples"
Requires-Dist: pandas>=1.4.0; extra == "examples"
Requires-Dist: palmerpenguins>=0.1.4; extra == "examples"
Requires-Dist: qatarcars>=0.3.0; extra == "examples"
Provides-Extra: all
Requires-Dist: sundar-gap-stat[dev,examples]; extra == "all"
Dynamic: license-file
